pytest_forbid/plugin.py
pytest_forbid-0.1.0.dist-info/WHEEL
pytest_forbid-0.1.0.dist-info/entry_points.txt
pytest_forbid-0.1.0.dist-info/METADATA
pytest_forbid-0.1.0.dist-info/RECORD
